5_df_even/even_circuit.v
// even_circuit.v -- A circuit the outputs 1 if input is an even number
//                   using dataflow modeling 
// SOP form: f(x, y, z) = \Sigma(0, 2, 4, 6)

// Syntax: module [design name] ([port list]):
// Description: Define the input and output interfaces of the hardware circuit
module even_circuit (
    // Syntax: input [width-1:0] <port name>
    input x,
    input y,
    input z,
    // Syntax: output [width-1:0] <port name>
    output f);

    // Truth table
    // | x | y | z | f | 
    // | - | - | - | - |
    // | 0 | 0 | 0 | 1 | 
    // | 0 | 0 | 1 | 0 | 
    // | 0 | 1 | 0 | 1 | 
    // | 0 | 1 | 1 | 0 | 
    // | 1 | 0 | 0 | 1 | 
    // | 1 | 0 | 1 | 0 | 
    // | 1 | 1 | 0 | 1 | 
    // | 1 | 1 | 1 | 0 | 

    //               (1)     (2)     (3)     (4)
    // f(x, y, z) = x'y'z' + x'yz' + xy'z' + xyz'

    // assign -- continuously assign a signal a value
    // Syntax: assign <output signal name>  = <operation on input signals>; 
    // && -- logical and operator
    // || -- logical or operator
    assign f = (~x && ~y && ~z) || 
               (~x && y && ~z) || 
               (x && ~y && ~z) || 
               (x && y && ~z);

// Syntax: endmodule: <module name>
endmodule: even_circuit

5_df_even/waveform.vcd
$version Generated by VerilatedVcd $end
$timescale 1s $end
 $scope module TOP $end
  $var wire 1 # x $end
  $var wire 1 $ y $end
  $var wire 1 % z $end
  $var wire 1 & f $end
  $scope module even_circuit $end
   $var wire 1 # x $end
   $var wire 1 $ y $end
   $var wire 1 % z $end
   $var wire 1 & f $end
  $upscope $end
 $upscope $end
$enddefinitions $end


#0
0#
0$
0%
1&
#1
1%
0&
#2
1$
0%
1&
#3
1%
0&
#4
1#
0$
0%
1&
#5
1%
0&
#6
1$
0%
1&
#7
1%
0&
